Workbook

Sheet README
A1: IREN — Damodaran-Style Scenario DCF Model
A3: Purpose | B3: Scenario-driven FCFF model linking growth, margins, reinvestment, ROIC, WACC and terminal value.
A4: Core philosophy | B4: Value = present value of expected cash flows. Price is an input for reverse DCF, not a valuation anchor.
A5: How to use | B5: Change yellow cells on Inputs and Scenarios sheets. Each scenario has its own DCF sheet (DCF-SevereBear through DCF-ExtremeBull); the Scenario Summary sheet probability-weights their results. Green cells are formulas/links. Blue cells are labels/structure.
A6: Primary outputs | B6: Five standalone scenario DCF values/share, probability-weighted value/share, expected upside/downside and annualized return, reverse-DCF implied growth/margin, sensitivity tables.
A7: Important | B7: This is a modeling framework, not a live market-data feed. Replace the initial assumptions with the latest filing/price data before making an investment decision.
A8: Model convention | B8: $ millions except per-share data, percentages and MW. FCFF is calculated from NOPAT less reinvestment.
A9: Model structure | B9: Five scenario DCF sheets, each a complete 10-year FCFF model with its own growth, margin, ROIC/reinvestment, WACC and terminal assumptions, feed a single probability-weighted Scenario Summary. The summary does not feed back into any DCF, so there are no circular references.

Sheet Inputs
A1: Inputs & Current Facts
A3: Current Market / Capital Structure
A4: Reference share price | B4: 45 | C4: $/share | D4: User-editable
A5: Diluted shares | B5: 380 | C5: mm | D5: Scenario assumption
A6: Cash | B6: 2600 | C6: $mm | D6: Approximate post-March cash
A7: Debt + finance leases | B7: 3800 | C7: $mm | D7: Approximate
A8: Net debt | B8: =B7-B6 | C8: $mm | D8: Debt less cash
A9: Current revenue run-rate | B9: 3700 | C9: $mm | D9: Management-target-style ARR anchor; replace with latest
A12: Base Operating / Valuation Assumptions
A13: Base revenue growth Y1 | B13: 0.45 | C13: % | D13: High-growth transition
A14: Growth decay per year | B14: 0.06 | C14: % pts | D14: Growth declines each year
A15: Base EBIT margin Y1 | B15: 0.25 | C15: % | D15: Editable
A16: Terminal EBIT margin | B16: 0.42 | C16: % | D16: Editable
A17: Tax rate | B17: 0.18 | C17: % | D17: Editable
A18: Base WACC | B18: 0.115 | C18: % | D18: Editable
A19: Terminal growth | B19: 0.03 | C19: % | D19: Must remain below WACC
A20: Terminal ROIC | B20: 0.15 | C20: % | D20: Stable-state assumption
A21: Initial ROIC | B21: 0.22 | C21: % | D21: Used for reinvestment
A22: Margin expansion per year | B22: 0.025 | C22: % pts | D22: Until terminal margin
A23: Minimum revenue growth | B23: 0.05 | C23: % | D23: Floor before terminal
A26: Scenario Multipliers / Overrides
A27: Use Scenario Sheet | B27: TRUE
A29: Bear | B29: Growth -15%; Margin -8 pts; WACC +1.5 pts
A30: Base | B30: Base assumptions
A31: Bull | B31: Growth +10%; Margin +5 pts; WACC -1 pt

Sheet Scenarios
A1: Scenario Controls
A3: Scenario Inputs
A4: Scenario | B4: Probability | C4: Growth Adj | D4: Margin Adj | E4: WACC Adj | F4: Terminal g Adj | G4: ROIC Adj | H4: Description
A5: Severe Bear | B5: 0.1 | C5: -0.25 | D5: -0.15 | E5: 0.025 | F5: -0.005 | G5: -0.05 | H5: AI economics deteriorate; high financing risk
A6: Bear | B6: 0.2 | C6: -0.15 | D6: -0.08 | E6: 0.015 | F6: -0.0025 | G6: -0.03 | H6: Slower AI growth, weaker margins
A7: Base | B7: 0.35 | C7: 0 | D7: 0 | E7: 0 | F7: 0 | G7: 0 | H7: Strong execution but normalized returns
A8: Bull | B8: 0.25 | C8: 0.1 | D8: 0.05 | E8: -0.01 | F8: 0.0025 | G8: 0.03 | H8: Strong utilization/pricing and execution
A9: Extreme Bull | B9: 0.1 | C9: 0.2 | D9: 0.1 | E9: -0.015 | F9: 0.005 | G9: 0.05 | H9: Exceptional AI platform economics
A12: Scenario DCF Sheets
A13: Severe Bear | B13: DCF-SevereBear
A14: Bear | B14: DCF-Bear
A15: Base | B15: DCF-Base
A16: Bull | B16: DCF-Bull
A17: Extreme Bull | B17: DCF-ExtremeBull
A19: Each scenario row feeds its own DCF sheet. Edit the five scenario rows above; the Scenario Summary sheet probability-weights the five DCF results.

Sheet DCF-SevereBear
A1: FCFF DCF — Severe Bear Scenario
A3: Severe Bear Scenario Assumptions
A4: Scenario | B4: =Scenarios!A5 | D4: Each scenario has its own complete 10-year DCF sheet. Adjustments pull from the matching row on the Scenarios sheet. Edit yellow cells on Inputs and Scenarios; green cells are formulas/links.
A5: Probability | B5: =Scenarios!B5
A6: Growth adjustment | B6: =Scenarios!C5
A7: Margin adjustment | B7: =Scenarios!D5
A8: WACC adjustment | B8: =Scenarios!E5
A9: Terminal g adjustment | B9: =Scenarios!F5
A10: ROIC adjustment | B10: =Scenarios!G5
A11: Effective WACC | B11: =Inputs!$B$18+$B$8
A12: Effective terminal growth | B12: =Inputs!$B$19+$B$9
A13: 10-Year Forecast
A14: Metric | B14: Y1 | C14: Y2 | D14: Y3 | E14: Y4 | F14: Y5 | G14: Y6 | H14: Y7 | I14: Y8 | J14: Y9 | K14: Y10
A15: Revenue | B15: =Inputs!$B$9*(1+MAX(Inputs!$B$13+($B$6),Inputs!$B$23)) | C15: =B15*(1+MAX(B16-Inputs!$B$14,Inputs!$B$23)) | D15: =C15*(1+MAX(C16-Inputs!$B$14,Inputs!$B$23)) | E15: =D15*(1+MAX(D16-Inputs!$B$14,Inputs!$B$23)) | F15: =E15*(1+MAX(E16-Inputs!$B$14,Inputs!$B$23)) | G15: =F15*(1+MAX(F16-Inputs!$B$14,Inputs!$B$23)) | H15: =G15*(1+MAX(G16-Inputs!$B$14,Inputs!$B$23)) | I15: =H15*(1+MAX(H16-Inputs!$B$14,Inputs!$B$23)) | J15: =I15*(1+MAX(I16-Inputs!$B$14,Inputs!$B$23)) | K15: =J15*(1+MAX(J16-Inputs!$B$14,Inputs!$B$23))
A16: Growth | B16: =B15/Inputs!$B$9-1 | C16: =MAX(B16-Inputs!$B$14,Inputs!$B$23) | D16: =MAX(C16-Inputs!$B$14,Inputs!$B$23) | E16: =MAX(D16-Inputs!$B$14,Inputs!$B$23) | F16: =MAX(E16-Inputs!$B$14,Inputs!$B$23) | G16: =MAX(F16-Inputs!$B$14,Inputs!$B$23) | H16: =MAX(G16-Inputs!$B$14,Inputs!$B$23) | I16: =MAX(H16-Inputs!$B$14,Inputs!$B$23) | J16: =MAX(I16-Inputs!$B$14,Inputs!$B$23) | K16: =MAX(J16-Inputs!$B$14,Inputs!$B$23)
A17: EBIT Margin | B17: =MIN(Inputs!$B$16+$B$7,Inputs!$B$15+$B$7+Inputs!$B$22*0) | C17: =MIN(Inputs!$B$16+$B$7,Inputs!$B$15+$B$7+Inputs!$B$22*1) | D17: =MIN(Inputs!$B$16+$B$7,Inputs!$B$15+$B$7+Inputs!$B$22*2) | E17: =MIN(Inputs!$B$16+$B$7,Inputs!$B$15+$B$7+Inputs!$B$22*3) | F17: =MIN(Inputs!$B$16+$B$7,Inputs!$B$15+$B$7+Inputs!$B$22*4) | G17: =MIN(Inputs!$B$16+$B$7,Inputs!$B$15+$B$7+Inputs!$B$22*5) | H17: =MIN(Inputs!$B$16+$B$7,Inputs!$B$15+$B$7+Inputs!$B$22*6) | I17: =MIN(Inputs!$B$16+$B$7,Inputs!$B$15+$B$7+Inputs!$B$22*7) | J17: =MIN(Inputs!$B$16+$B$7,Inputs!$B$15+$B$7+Inputs!$B$22*8) | K17: =MIN(Inputs!$B$16+$B$7,Inputs!$B$15+$B$7+Inputs!$B$22*9)
A18: EBIT | B18: =B15*B17 | C18: =C15*C17 | D18: =D15*D17 | E18: =E15*E17 | F18: =F15*F17 | G18: =G15*G17 | H18: =H15*H17 | I18: =I15*I17 | ... K18: =K15*K17
A19: Tax | B19: =Inputs!$B$17 | C19: =Inputs!$B$17 | D19: =Inputs!$B$17 | E19: =Inputs!$B$17 | F19: =Inputs!$B$17 | G19: =Inputs!$B$17 | H19: =Inputs!$B$17 | I19: =Inputs!$B$17 | ... K19: =Inputs!$B$17
A20: NOPAT | B20: =B18*(1-B19) | C20: =C18*(1-C19) | D20: =D18*(1-D19) | E20: =E18*(1-E19) | F20: =F18*(1-F19) | G20: =G18*(1-G19) | H20: =H18*(1-H19) | I20: =I18*(1-I19) | ... K20: =K18*(1-K19)
A21: ROIC | B21: =MAX(Inputs!$B$20+$B$10,Inputs!$B$21+$B$10-(Inputs!$B$21-Inputs!$B$20)*0/9) | C21: =MAX(Inputs!$B$20+$B$10,Inputs!$B$21+$B$10-(Inputs!$B$21-Inputs!$B$20)*1/9) | D21: =MAX(Inputs!$B$20+$B$10,Inputs!$B$21+$B$10-(Inputs!$B$21-Inputs!$B$20)*2/9) | E21: =MAX(Inputs!$B$20+$B$10,Inputs!$B$21+$B$10-(Inputs!$B$21-Inputs!$B$20)*3/9) | F21: =MAX(Inputs!$B$20+$B$10,Inputs!$B$21+$B$10-(Inputs!$B$21-Inputs!$B$20)*4/9) | G21: =MAX(Inputs!$B$20+$B$10,Inputs!$B$21+$B$10-(Inputs!$B$21-Inputs!$B$20)*5/9) | H21: =MAX(Inputs!$B$20+$B$10,Inputs!$B$21+$B$10-(Inputs!$B$21-Inputs!$B$20)*6/9) | I21: =MAX(Inputs!$B$20+$B$10,Inputs!$B$21+$B$10-(Inputs!$B$21-Inputs!$B$20)*7/9) | J21: =MAX(Inputs!$B$20+$B$10,Inputs!$B$21+$B$10-(Inputs!$B$21-Inputs!$B$20)*8/9) | K21: =MAX(Inputs!$B$20+$B$10,Inputs!$B$21+$B$10-(Inputs!$B$21-Inputs!$B$20)*9/9)
A22: Reinvestment Rate | B22: =B16/B21 | C22: =C16/C21 | D22: =D16/D21 | E22: =E16/E21 | F22: =F16/F21 | G22: =G16/G21 | H22: =H16/H21 | I22: =I16/I21 | ... K22: =K16/K21
A23: Reinvestment | B23: =B20*B22 | C23: =C20*C22 | D23: =D20*D22 | E23: =E20*E22 | F23: =F20*F22 | G23: =G20*G22 | H23: =H20*H22 | I23: =I20*I22 | ... K23: =K20*K22
A24: FCFF | B24: =B20-B23 | C24: =C20-C23 | D24: =D20-D23 | E24: =E20-E23 | F24: =F20-F23 | G24: =G20-G23 | H24: =H20-H23 | I24: =I20-I23 | ... K24: =K20-K23
A25: Discount Factor | B25: =1/(1+$B$11)^1 | C25: =1/(1+$B$11)^2 | D25: =1/(1+$B$11)^3 | E25: =1/(1+$B$11)^4 | F25: =1/(1+$B$11)^5 | G25: =1/(1+$B$11)^6 | H25: =1/(1+$B$11)^7 | I25: =1/(1+$B$11)^8 | J25: =1/(1+$B$11)^9 | K25: =1/(1+$B$11)^10
A26: PV of FCFF | B26: =B24*B25 | C26: =C24*C25 | D26: =D24*D25 | E26: =E24*E25 | F26: =F24*F25 | G26: =G24*G25 | H26: =H24*H25 | I26: =I24*I25 | ... K26: =K24*K25
A29: Terminal Value & Equity Value
A30: Terminal growth | B30: =$B$12
A31: Terminal ROIC | B31: =Inputs!$B$20+$B$10
A32: Terminal reinvestment rate | B32: =B30/B31
A33: Terminal FCFF | B33: =K20*(1+B30)*(1-B32)
A34: Terminal value | B34: =B33/($B$11-B30)
A35: PV of explicit FCFF | B35: =SUM(B26:K26)
A36: PV of terminal value | B36: =B34/(1+$B$11)^10
A37: Enterprise value | B37: =B35+B36
A38: Less net debt | B38: =Inputs!$B$8
A39: Equity value | B39: =B37-B38
A40: Diluted shares | B40: =Inputs!$B$5
A41: Intrinsic value / share | B41: =B39/B40
A42: Terminal value / EV | B42: =B36/B37

Sheet DCF-Bear
A1: FCFF DCF — Bear Scenario
A3: Bear Scenario Assumptions
A4: Scenario | B4: =Scenarios!A6 | D4: Each scenario has its own complete 10-year DCF sheet. Adjustments pull from the matching row on the Scenarios sheet. Edit yellow cells on Inputs and Scenarios; green cells are formulas/links.
A5: Probability | B5: =Scenarios!B6
A6: Growth adjustment | B6: =Scenarios!C6
A7: Margin adjustment | B7: =Scenarios!D6
A8: WACC adjustment | B8: =Scenarios!E6
A9: Terminal g adjustment | B9: =Scenarios!F6
A10: ROIC adjustment | B10: =Scenarios!G6
A11: Effective WACC | B11: =Inputs!$B$18+$B$8
A12: Effective terminal growth | B12: =Inputs!$B$19+$B$9
A13: 10-Year Forecast
A14: Metric | B14: Y1 | C14: Y2 | D14: Y3 | E14: Y4 | F14: Y5 | G14: Y6 | H14: Y7 | I14: Y8 | J14: Y9 | K14: Y10
A15: Revenue | B15: =Inputs!$B$9*(1+MAX(Inputs!$B$13+($B$6),Inputs!$B$23)) | C15: =B15*(1+MAX(B16-Inputs!$B$14,Inputs!$B$23)) | D15: =C15*(1+MAX(C16-Inputs!$B$14,Inputs!$B$23)) | E15: =D15*(1+MAX(D16-Inputs!$B$14,Inputs!$B$23)) | F15: =E15*(1+MAX(E16-Inputs!$B$14,Inputs!$B$23)) | G15: =F15*(1+MAX(F16-Inputs!$B$14,Inputs!$B$23)) | H15: =G15*(1+MAX(G16-Inputs!$B$14,Inputs!$B$23)) | I15: =H15*(1+MAX(H16-Inputs!$B$14,Inputs!$B$23)) | J15: =I15*(1+MAX(I16-Inputs!$B$14,Inputs!$B$23)) | K15: =J15*(1+MAX(J16-Inputs!$B$14,Inputs!$B$23))
A16: Growth | B16: =B15/Inputs!$B$9-1 | C16: =MAX(B16-Inputs!$B$14,Inputs!$B$23) | D16: =MAX(C16-Inputs!$B$14,Inputs!$B$23) | E16: =MAX(D16-Inputs!$B$14,Inputs!$B$23) | F16: =MAX(E16-Inputs!$B$14,Inputs!$B$23) | G16: =MAX(F16-Inputs!$B$14,Inputs!$B$23) | H16: =MAX(G16-Inputs!$B$14,Inputs!$B$23) | I16: =MAX(H16-Inputs!$B$14,Inputs!$B$23) | J16: =MAX(I16-Inputs!$B$14,Inputs!$B$23) | K16: =MAX(J16-Inputs!$B$14,Inputs!$B$23)
A17: EBIT Margin | B17: =MIN(Inputs!$B$16+$B$7,Inputs!$B$15+$B$7+Inputs!$B$22*0) | C17: =MIN(Inputs!$B$16+$B$7,Inputs!$B$15+$B$7+Inputs!$B$22*1) | D17: =MIN(Inputs!$B$16+$B$7,Inputs!$B$15+$B$7+Inputs!$B$22*2) | E17: =MIN(Inputs!$B$16+$B$7,Inputs!$B$15+$B$7+Inputs!$B$22*3) | F17: =MIN(Inputs!$B$16+$B$7,Inputs!$B$15+$B$7+Inputs!$B$22*4) | G17: =MIN(Inputs!$B$16+$B$7,Inputs!$B$15+$B$7+Inputs!$B$22*5) | H17: =MIN(Inputs!$B$16+$B$7,Inputs!$B$15+$B$7+Inputs!$B$22*6) | I17: =MIN(Inputs!$B$16+$B$7,Inputs!$B$15+$B$7+Inputs!$B$22*7) | J17: =MIN(Inputs!$B$16+$B$7,Inputs!$B$15+$B$7+Inputs!$B$22*8) | K17: =MIN(Inputs!$B$16+$B$7,Inputs!$B$15+$B$7+Inputs!$B$22*9)
A18: EBIT | B18: =B15*B17 | C18: =C15*C17 | D18: =D15*D17 | E18: =E15*E17 | F18: =F15*F17 | G18: =G15*G17 | H18: =H15*H17 | I18: =I15*I17 | ... K18: =K15*K17
A19: Tax | B19: =Inputs!$B$17 | C19: =Inputs!$B$17 | D19: =Inputs!$B$17 | E19: =Inputs!$B$17 | F19: =Inputs!$B$17 | G19: =Inputs!$B$17 | H19: =Inputs!$B$17 | I19: =Inputs!$B$17 | ... K19: =Inputs!$B$17
A20: NOPAT | B20: =B18*(1-B19) | C20: =C18*(1-C19) | D20: =D18*(1-D19) | E20: =E18*(1-E19) | F20: =F18*(1-F19) | G20: =G18*(1-G19) | H20: =H18*(1-H19) | I20: =I18*(1-I19) | ... K20: =K18*(1-K19)
A21: ROIC | B21: =MAX(Inputs!$B$20+$B$10,Inputs!$B$21+$B$10-(Inputs!$B$21-Inputs!$B$20)*0/9) | C21: =MAX(Inputs!$B$20+$B$10,Inputs!$B$21+$B$10-(Inputs!$B$21-Inputs!$B$20)*1/9) | D21: =MAX(Inputs!$B$20+$B$10,Inputs!$B$21+$B$10-(Inputs!$B$21-Inputs!$B$20)*2/9) | E21: =MAX(Inputs!$B$20+$B$10,Inputs!$B$21+$B$10-(Inputs!$B$21-Inputs!$B$20)*3/9) | F21: =MAX(Inputs!$B$20+$B$10,Inputs!$B$21+$B$10-(Inputs!$B$21-Inputs!$B$20)*4/9) | G21: =MAX(Inputs!$B$20+$B$10,Inputs!$B$21+$B$10-(Inputs!$B$21-Inputs!$B$20)*5/9) | H21: =MAX(Inputs!$B$20+$B$10,Inputs!$B$21+$B$10-(Inputs!$B$21-Inputs!$B$20)*6/9) | I21: =MAX(Inputs!$B$20+$B$10,Inputs!$B$21+$B$10-(Inputs!$B$21-Inputs!$B$20)*7/9) | J21: =MAX(Inputs!$B$20+$B$10,Inputs!$B$21+$B$10-(Inputs!$B$21-Inputs!$B$20)*8/9) | K21: =MAX(Inputs!$B$20+$B$10,Inputs!$B$21+$B$10-(Inputs!$B$21-Inputs!$B$20)*9/9)
A22: Reinvestment Rate | B22: =B16/B21 | C22: =C16/C21 | D22: =D16/D21 | E22: =E16/E21 | F22: =F16/F21 | G22: =G16/G21 | H22: =H16/H21 | I22: =I16/I21 | ... K22: =K16/K21
A23: Reinvestment | B23: =B20*B22 | C23: =C20*C22 | D23: =D20*D22 | E23: =E20*E22 | F23: =F20*F22 | G23: =G20*G22 | H23: =H20*H22 | I23: =I20*I22 | ... K23: =K20*K22
A24: FCFF | B24: =B20-B23 | C24: =C20-C23 | D24: =D20-D23 | E24: =E20-E23 | F24: =F20-F23 | G24: =G20-G23 | H24: =H20-H23 | I24: =I20-I23 | ... K24: =K20-K23
A25: Discount Factor | B25: =1/(1+$B$11)^1 | C25: =1/(1+$B$11)^2 | D25: =1/(1+$B$11)^3 | E25: =1/(1+$B$11)^4 | F25: =1/(1+$B$11)^5 | G25: =1/(1+$B$11)^6 | H25: =1/(1+$B$11)^7 | I25: =1/(1+$B$11)^8 | J25: =1/(1+$B$11)^9 | K25: =1/(1+$B$11)^10
A26: PV of FCFF | B26: =B24*B25 | C26: =C24*C25 | D26: =D24*D25 | E26: =E24*E25 | F26: =F24*F25 | G26: =G24*G25 | H26: =H24*H25 | I26: =I24*I25 | ... K26: =K24*K25
A29: Terminal Value & Equity Value
A30: Terminal growth | B30: =$B$12
A31: Terminal ROIC | B31: =Inputs!$B$20+$B$10
A32: Terminal reinvestment rate | B32: =B30/B31
A33: Terminal FCFF | B33: =K20*(1+B30)*(1-B32)
A34: Terminal value | B34: =B33/($B$11-B30)
A35: PV of explicit FCFF | B35: =SUM(B26:K26)
A36: PV of terminal value | B36: =B34/(1+$B$11)^10
A37: Enterprise value | B37: =B35+B36
A38: Less net debt | B38: =Inputs!$B$8
A39: Equity value | B39: =B37-B38
A40: Diluted shares | B40: =Inputs!$B$5
A41: Intrinsic value / share | B41: =B39/B40
A42: Terminal value / EV | B42: =B36/B37

Sheet DCF-Base
A1: FCFF DCF — Base Scenario
A3: Base Scenario Assumptions
A4: Scenario | B4: =Scenarios!A7 | D4: Each scenario has its own complete 10-year DCF sheet. Adjustments pull from the matching row on the Scenarios sheet. Edit yellow cells on Inputs and Scenarios; green cells are formulas/links.
A5: Probability | B5: =Scenarios!B7
A6: Growth adjustment | B6: =Scenarios!C7
A7: Margin adjustment | B7: =Scenarios!D7
A8: WACC adjustment | B8: =Scenarios!E7
A9: Terminal g adjustment | B9: =Scenarios!F7
A10: ROIC adjustment | B10: =Scenarios!G7
A11: Effective WACC | B11: =Inputs!$B$18+$B$8
A12: Effective terminal growth | B12: =Inputs!$B$19+$B$9
A13: 10-Year Forecast
A14: Metric | B14: Y1 | C14: Y2 | D14: Y3 | E14: Y4 | F14: Y5 | G14: Y6 | H14: Y7 | I14: Y8 | J14: Y9 | K14: Y10
A15: Revenue | B15: =Inputs!$B$9*(1+MAX(Inputs!$B$13+($B$6),Inputs!$B$23)) | C15: =B15*(1+MAX(B16-Inputs!$B$14,Inputs!$B$23)) | D15: =C15*(1+MAX(C16-Inputs!$B$14,Inputs!$B$23)) | E15: =D15*(1+MAX(D16-Inputs!$B$14,Inputs!$B$23)) | F15: =E15*(1+MAX(E16-Inputs!$B$14,Inputs!$B$23)) | G15: =F15*(1+MAX(F16-Inputs!$B$14,Inputs!$B$23)) | H15: =G15*(1+MAX(G16-Inputs!$B$14,Inputs!$B$23)) | I15: =H15*(1+MAX(H16-Inputs!$B$14,Inputs!$B$23)) | J15: =I15*(1+MAX(I16-Inputs!$B$14,Inputs!$B$23)) | K15: =J15*(1+MAX(J16-Inputs!$B$14,Inputs!$B$23))
A16: Growth | B16: =B15/Inputs!$B$9-1 | C16: =MAX(B16-Inputs!$B$14,Inputs!$B$23) | D16: =MAX(C16-Inputs!$B$14,Inputs!$B$23) | E16: =MAX(D16-Inputs!$B$14,Inputs!$B$23) | F16: =MAX(E16-Inputs!$B$14,Inputs!$B$23) | G16: =MAX(F16-Inputs!$B$14,Inputs!$B$23) | H16: =MAX(G16-Inputs!$B$14,Inputs!$B$23) | I16: =MAX(H16-Inputs!$B$14,Inputs!$B$23) | J16: =MAX(I16-Inputs!$B$14,Inputs!$B$23) | K16: =MAX(J16-Inputs!$B$14,Inputs!$B$23)
A17: EBIT Margin | B17: =MIN(Inputs!$B$16+$B$7,Inputs!$B$15+$B$7+Inputs!$B$22*0) | C17: =MIN(Inputs!$B$16+$B$7,Inputs!$B$15+$B$7+Inputs!$B$22*1) | D17: =MIN(Inputs!$B$16+$B$7,Inputs!$B$15+$B$7+Inputs!$B$22*2) | E17: =MIN(Inputs!$B$16+$B$7,Inputs!$B$15+$B$7+Inputs!$B$22*3) | F17: =MIN(Inputs!$B$16+$B$7,Inputs!$B$15+$B$7+Inputs!$B$22*4) | G17: =MIN(Inputs!$B$16+$B$7,Inputs!$B$15+$B$7+Inputs!$B$22*5) | H17: =MIN(Inputs!$B$16+$B$7,Inputs!$B$15+$B$7+Inputs!$B$22*6) | I17: =MIN(Inputs!$B$16+$B$7,Inputs!$B$15+$B$7+Inputs!$B$22*7) | J17: =MIN(Inputs!$B$16+$B$7,Inputs!$B$15+$B$7+Inputs!$B$22*8) | K17: =MIN(Inputs!$B$16+$B$7,Inputs!$B$15+$B$7+Inputs!$B$22*9)
A18: EBIT | B18: =B15*B17 | C18: =C15*C17 | D18: =D15*D17 | E18: =E15*E17 | F18: =F15*F17 | G18: =G15*G17 | H18: =H15*H17 | I18: =I15*I17 | ... K18: =K15*K17
A19: Tax | B19: =Inputs!$B$17 | C19: =Inputs!$B$17 | D19: =Inputs!$B$17 | E19: =Inputs!$B$17 | F19: =Inputs!$B$17 | G19: =Inputs!$B$17 | H19: =Inputs!$B$17 | I19: =Inputs!$B$17 | ... K19: =Inputs!$B$17
A20: NOPAT | B20: =B18*(1-B19) | C20: =C18*(1-C19) | D20: =D18*(1-D19) | E20: =E18*(1-E19) | F20: =F18*(1-F19) | G20: =G18*(1-G19) | H20: =H18*(1-H19) | I20: =I18*(1-I19) | ... K20: =K18*(1-K19)
A21: ROIC | B21: =MAX(Inputs!$B$20+$B$10,Inputs!$B$21+$B$10-(Inputs!$B$21-Inputs!$B$20)*0/9) | C21: =MAX(Inputs!$B$20+$B$10,Inputs!$B$21+$B$10-(Inputs!$B$21-Inputs!$B$20)*1/9) | D21: =MAX(Inputs!$B$20+$B$10,Inputs!$B$21+$B$10-(Inputs!$B$21-Inputs!$B$20)*2/9) | E21: =MAX(Inputs!$B$20+$B$10,Inputs!$B$21+$B$10-(Inputs!$B$21-Inputs!$B$20)*3/9) | F21: =MAX(Inputs!$B$20+$B$10,Inputs!$B$21+$B$10-(Inputs!$B$21-Inputs!$B$20)*4/9) | G21: =MAX(Inputs!$B$20+$B$10,Inputs!$B$21+$B$10-(Inputs!$B$21-Inputs!$B$20)*5/9) | H21: =MAX(Inputs!$B$20+$B$10,Inputs!$B$21+$B$10-(Inputs!$B$21-Inputs!$B$20)*6/9) | I21: =MAX(Inputs!$B$20+$B$10,Inputs!$B$21+$B$10-(Inputs!$B$21-Inputs!$B$20)*7/9) | J21: =MAX(Inputs!$B$20+$B$10,Inputs!$B$21+$B$10-(Inputs!$B$21-Inputs!$B$20)*8/9) | K21: =MAX(Inputs!$B$20+$B$10,Inputs!$B$21+$B$10-(Inputs!$B$21-Inputs!$B$20)*9/9)
A22: Reinvestment Rate | B22: =B16/B21 | C22: =C16/C21 | D22: =D16/D21 | E22: =E16/E21 | F22: =F16/F21 | G22: =G16/G21 | H22: =H16/H21 | I22: =I16/I21 | ... K22: =K16/K21
A23: Reinvestment | B23: =B20*B22 | C23: =C20*C22 | D23: =D20*D22 | E23: =E20*E22 | F23: =F20*F22 | G23: =G20*G22 | H23: =H20*H22 | I23: =I20*I22 | ... K23: =K20*K22
A24: FCFF | B24: =B20-B23 | C24: =C20-C23 | D24: =D20-D23 | E24: =E20-E23 | F24: =F20-F23 | G24: =G20-G23 | H24: =H20-H23 | I24: =I20-I23 | ... K24: =K20-K23
A25: Discount Factor | B25: =1/(1+$B$11)^1 | C25: =1/(1+$B$11)^2 | D25: =1/(1+$B$11)^3 | E25: =1/(1+$B$11)^4 | F25: =1/(1+$B$11)^5 | G25: =1/(1+$B$11)^6 | H25: =1/(1+$B$11)^7 | I25: =1/(1+$B$11)^8 | J25: =1/(1+$B$11)^9 | K25: =1/(1+$B$11)^10
A26: PV of FCFF | B26: =B24*B25 | C26: =C24*C25 | D26: =D24*D25 | E26: =E24*E25 | F26: =F24*F25 | G26: =G24*G25 | H26: =H24*H25 | I26: =I24*I25 | ... K26: =K24*K25
A29: Terminal Value & Equity Value
A30: Terminal growth | B30: =$B$12
A31: Terminal ROIC | B31: =Inputs!$B$20+$B$10
A32: Terminal reinvestment rate | B32: =B30/B31
A33: Terminal FCFF | B33: =K20*(1+B30)*(1-B32)
A34: Terminal value | B34: =B33/($B$11-B30)
A35: PV of explicit FCFF | B35: =SUM(B26:K26)
A36: PV of terminal value | B36: =B34/(1+$B$11)^10
A37: Enterprise value | B37: =B35+B36
A38: Less net debt | B38: =Inputs!$B$8
A39: Equity value | B39: =B37-B38
A40: Diluted shares | B40: =Inputs!$B$5
A41: Intrinsic value / share | B41: =B39/B40
A42: Terminal value / EV | B42: =B36/B37

Sheet DCF-Bull
A1: FCFF DCF — Bull Scenario
A3: Bull Scenario Assumptions
A4: Scenario | B4: =Scenarios!A8 | D4: Each scenario has its own complete 10-year DCF sheet. Adjustments pull from the matching row on the Scenarios sheet. Edit yellow cells on Inputs and Scenarios; green cells are formulas/links.
A5: Probability | B5: =Scenarios!B8
A6: Growth adjustment | B6: =Scenarios!C8
A7: Margin adjustment | B7: =Scenarios!D8
A8: WACC adjustment | B8: =Scenarios!E8
A9: Terminal g adjustment | B9: =Scenarios!F8
A10: ROIC adjustment | B10: =Scenarios!G8
A11: Effective WACC | B11: =Inputs!$B$18+$B$8
A12: Effective terminal growth | B12: =Inputs!$B$19+$B$9
A13: 10-Year Forecast
A14: Metric | B14: Y1 | C14: Y2 | D14: Y3 | E14: Y4 | F14: Y5 | G14: Y6 | H14: Y7 | I14: Y8 | J14: Y9 | K14: Y10
A15: Revenue | B15: =Inputs!$B$9*(1+MAX(Inputs!$B$13+($B$6),Inputs!$B$23)) | C15: =B15*(1+MAX(B16-Inputs!$B$14,Inputs!$B$23)) | D15: =C15*(1+MAX(C16-Inputs!$B$14,Inputs!$B$23)) | E15: =D15*(1+MAX(D16-Inputs!$B$14,Inputs!$B$23)) | F15: =E15*(1+MAX(E16-Inputs!$B$14,Inputs!$B$23)) | G15: =F15*(1+MAX(F16-Inputs!$B$14,Inputs!$B$23)) | H15: =G15*(1+MAX(G16-Inputs!$B$14,Inputs!$B$23)) | I15: =H15*(1+MAX(H16-Inputs!$B$14,Inputs!$B$23)) | J15: =I15*(1+MAX(I16-Inputs!$B$14,Inputs!$B$23)) | K15: =J15*(1+MAX(J16-Inputs!$B$14,Inputs!$B$23))
A16: Growth | B16: =B15/Inputs!$B$9-1 | C16: =MAX(B16-Inputs!$B$14,Inputs!$B$23) | D16: =MAX(C16-Inputs!$B$14,Inputs!$B$23) | E16: =MAX(D16-Inputs!$B$14,Inputs!$B$23) | F16: =MAX(E16-Inputs!$B$14,Inputs!$B$23) | G16: =MAX(F16-Inputs!$B$14,Inputs!$B$23) | H16: =MAX(G16-Inputs!$B$14,Inputs!$B$23) | I16: =MAX(H16-Inputs!$B$14,Inputs!$B$23) | J16: =MAX(I16-Inputs!$B$14,Inputs!$B$23) | K16: =MAX(J16-Inputs!$B$14,Inputs!$B$23)
A17: EBIT Margin | B17: =MIN(Inputs!$B$16+$B$7,Inputs!$B$15+$B$7+Inputs!$B$22*0) | C17: =MIN(Inputs!$B$16+$B$7,Inputs!$B$15+$B$7+Inputs!$B$22*1) | D17: =MIN(Inputs!$B$16+$B$7,Inputs!$B$15+$B$7+Inputs!$B$22*2) | E17: =MIN(Inputs!$B$16+$B$7,Inputs!$B$15+$B$7+Inputs!$B$22*3) | F17: =MIN(Inputs!$B$16+$B$7,Inputs!$B$15+$B$7+Inputs!$B$22*4) | G17: =MIN(Inputs!$B$16+$B$7,Inputs!$B$15+$B$7+Inputs!$B$22*5) | H17: =MIN(Inputs!$B$16+$B$7,Inputs!$B$15+$B$7+Inputs!$B$22*6) | I17: =MIN(Inputs!$B$16+$B$7,Inputs!$B$15+$B$7+Inputs!$B$22*7) | J17: =MIN(Inputs!$B$16+$B$7,Inputs!$B$15+$B$7+Inputs!$B$22*8) | K17: =MIN(Inputs!$B$16+$B$7,Inputs!$B$15+$B$7+Inputs!$B$22*9)
A18: EBIT | B18: =B15*B17 | C18: =C15*C17 | D18: =D15*D17 | E18: =E15*E17 | F18: =F15*F17 | G18: =G15*G17 | H18: =H15*H17 | I18: =I15*I17 | ... K18: =K15*K17
A19: Tax | B19: =Inputs!$B$17 | C19: =Inputs!$B$17 | D19: =Inputs!$B$17 | E19: =Inputs!$B$17 | F19: =Inputs!$B$17 | G19: =Inputs!$B$17 | H19: =Inputs!$B$17 | I19: =Inputs!$B$17 | ... K19: =Inputs!$B$17
A20: NOPAT | B20: =B18*(1-B19) | C20: =C18*(1-C19) | D20: =D18*(1-D19) | E20: =E18*(1-E19) | F20: =F18*(1-F19) | G20: =G18*(1-G19) | H20: =H18*(1-H19) | I20: =I18*(1-I19) | ... K20: =K18*(1-K19)
A21: ROIC | B21: =MAX(Inputs!$B$20+$B$10,Inputs!$B$21+$B$10-(Inputs!$B$21-Inputs!$B$20)*0/9) | C21: =MAX(Inputs!$B$20+$B$10,Inputs!$B$21+$B$10-(Inputs!$B$21-Inputs!$B$20)*1/9) | D21: =MAX(Inputs!$B$20+$B$10,Inputs!$B$21+$B$10-(Inputs!$B$21-Inputs!$B$20)*2/9) | E21: =MAX(Inputs!$B$20+$B$10,Inputs!$B$21+$B$10-(Inputs!$B$21-Inputs!$B$20)*3/9) | F21: =MAX(Inputs!$B$20+$B$10,Inputs!$B$21+$B$10-(Inputs!$B$21-Inputs!$B$20)*4/9) | G21: =MAX(Inputs!$B$20+$B$10,Inputs!$B$21+$B$10-(Inputs!$B$21-Inputs!$B$20)*5/9) | H21: =MAX(Inputs!$B$20+$B$10,Inputs!$B$21+$B$10-(Inputs!$B$21-Inputs!$B$20)*6/9) | I21: =MAX(Inputs!$B$20+$B$10,Inputs!$B$21+$B$10-(Inputs!$B$21-Inputs!$B$20)*7/9) | J21: =MAX(Inputs!$B$20+$B$10,Inputs!$B$21+$B$10-(Inputs!$B$21-Inputs!$B$20)*8/9) | K21: =MAX(Inputs!$B$20+$B$10,Inputs!$B$21+$B$10-(Inputs!$B$21-Inputs!$B$20)*9/9)
A22: Reinvestment Rate | B22: =B16/B21 | C22: =C16/C21 | D22: =D16/D21 | E22: =E16/E21 | F22: =F16/F21 | G22: =G16/G21 | H22: =H16/H21 | I22: =I16/I21 | ... K22: =K16/K21
A23: Reinvestment | B23: =B20*B22 | C23: =C20*C22 | D23: =D20*D22 | E23: =E20*E22 | F23: =F20*F22 | G23: =G20*G22 | H23: =H20*H22 | I23: =I20*I22 | ... K23: =K20*K22
A24: FCFF | B24: =B20-B23 | C24: =C20-C23 | D24: =D20-D23 | E24: =E20-E23 | F24: =F20-F23 | G24: =G20-G23 | H24: =H20-H23 | I24: =I20-I23 | ... K24: =K20-K23
A25: Discount Factor | B25: =1/(1+$B$11)^1 | C25: =1/(1+$B$11)^2 | D25: =1/(1+$B$11)^3 | E25: =1/(1+$B$11)^4 | F25: =1/(1+$B$11)^5 | G25: =1/(1+$B$11)^6 | H25: =1/(1+$B$11)^7 | I25: =1/(1+$B$11)^8 | J25: =1/(1+$B$11)^9 | K25: =1/(1+$B$11)^10
A26: PV of FCFF | B26: =B24*B25 | C26: =C24*C25 | D26: =D24*D25 | E26: =E24*E25 | F26: =F24*F25 | G26: =G24*G25 | H26: =H24*H25 | I26: =I24*I25 | ... K26: =K24*K25
A29: Terminal Value & Equity Value
A30: Terminal growth | B30: =$B$12
A31: Terminal ROIC | B31: =Inputs!$B$20+$B$10
A32: Terminal reinvestment rate | B32: =B30/B31
A33: Terminal FCFF | B33: =K20*(1+B30)*(1-B32)
A34: Terminal value | B34: =B33/($B$11-B30)
A35: PV of explicit FCFF | B35: =SUM(B26:K26)
A36: PV of terminal value | B36: =B34/(1+$B$11)^10
A37: Enterprise value | B37: =B35+B36
A38: Less net debt | B38: =Inputs!$B$8
A39: Equity value | B39: =B37-B38
A40: Diluted shares | B40: =Inputs!$B$5
A41: Intrinsic value / share | B41: =B39/B40
A42: Terminal value / EV | B42: =B36/B37

Sheet DCF-ExtremeBull
A1: FCFF DCF — Extreme Bull Scenario
A3: Extreme Bull Scenario Assumptions
A4: Scenario | B4: =Scenarios!A9 | D4: Each scenario has its own complete 10-year DCF sheet. Adjustments pull from the matching row on the Scenarios sheet. Edit yellow cells on Inputs and Scenarios; green cells are formulas/links.
A5: Probability | B5: =Scenarios!B9
A6: Growth adjustment | B6: =Scenarios!C9
A7: Margin adjustment | B7: =Scenarios!D9
A8: WACC adjustment | B8: =Scenarios!E9
A9: Terminal g adjustment | B9: =Scenarios!F9
A10: ROIC adjustment | B10: =Scenarios!G9
A11: Effective WACC | B11: =Inputs!$B$18+$B$8
A12: Effective terminal growth | B12: =Inputs!$B$19+$B$9
A13: 10-Year Forecast
A14: Metric | B14: Y1 | C14: Y2 | D14: Y3 | E14: Y4 | F14: Y5 | G14: Y6 | H14: Y7 | I14: Y8 | J14: Y9 | K14: Y10
A15: Revenue | B15: =Inputs!$B$9*(1+MAX(Inputs!$B$13+($B$6),Inputs!$B$23)) | C15: =B15*(1+MAX(B16-Inputs!$B$14,Inputs!$B$23)) | D15: =C15*(1+MAX(C16-Inputs!$B$14,Inputs!$B$23)) | E15: =D15*(1+MAX(D16-Inputs!$B$14,Inputs!$B$23)) | F15: =E15*(1+MAX(E16-Inputs!$B$14,Inputs!$B$23)) | G15: =F15*(1+MAX(F16-Inputs!$B$14,Inputs!$B$23)) | H15: =G15*(1+MAX(G16-Inputs!$B$14,Inputs!$B$23)) | I15: =H15*(1+MAX(H16-Inputs!$B$14,Inputs!$B$23)) | J15: =I15*(1+MAX(I16-Inputs!$B$14,Inputs!$B$23)) | K15: =J15*(1+MAX(J16-Inputs!$B$14,Inputs!$B$23))
A16: Growth | B16: =B15/Inputs!$B$9-1 | C16: =MAX(B16-Inputs!$B$14,Inputs!$B$23) | D16: =MAX(C16-Inputs!$B$14,Inputs!$B$23) | E16: =MAX(D16-Inputs!$B$14,Inputs!$B$23) | F16: =MAX(E16-Inputs!$B$14,Inputs!$B$23) | G16: =MAX(F16-Inputs!$B$14,Inputs!$B$23) | H16: =MAX(G16-Inputs!$B$14,Inputs!$B$23) | I16: =MAX(H16-Inputs!$B$14,Inputs!$B$23) | J16: =MAX(I16-Inputs!$B$14,Inputs!$B$23) | K16: =MAX(J16-Inputs!$B$14,Inputs!$B$23)
A17: EBIT Margin | B17: =MIN(Inputs!$B$16+$B$7,Inputs!$B$15+$B$7+Inputs!$B$22*0) | C17: =MIN(Inputs!$B$16+$B$7,Inputs!$B$15+$B$7+Inputs!$B$22*1) | D17: =MIN(Inputs!$B$16+$B$7,Inputs!$B$15+$B$7+Inputs!$B$22*2) | E17: =MIN(Inputs!$B$16+$B$7,Inputs!$B$15+$B$7+Inputs!$B$22*3) | F17: =MIN(Inputs!$B$16+$B$7,Inputs!$B$15+$B$7+Inputs!$B$22*4) | G17: =MIN(Inputs!$B$16+$B$7,Inputs!$B$15+$B$7+Inputs!$B$22*5) | H17: =MIN(Inputs!$B$16+$B$7,Inputs!$B$15+$B$7+Inputs!$B$22*6) | I17: =MIN(Inputs!$B$16+$B$7,Inputs!$B$15+$B$7+Inputs!$B$22*7) | J17: =MIN(Inputs!$B$16+$B$7,Inputs!$B$15+$B$7+Inputs!$B$22*8) | K17: =MIN(Inputs!$B$16+$B$7,Inputs!$B$15+$B$7+Inputs!$B$22*9)
A18: EBIT | B18: =B15*B17 | C18: =C15*C17 | D18: =D15*D17 | E18: =E15*E17 | F18: =F15*F17 | G18: =G15*G17 | H18: =H15*H17 | I18: =I15*I17 | ... K18: =K15*K17
A19: Tax | B19: =Inputs!$B$17 | C19: =Inputs!$B$17 | D19: =Inputs!$B$17 | E19: =Inputs!$B$17 | F19: =Inputs!$B$17 | G19: =Inputs!$B$17 | H19: =Inputs!$B$17 | I19: =Inputs!$B$17 | ... K19: =Inputs!$B$17
A20: NOPAT | B20: =B18*(1-B19) | C20: =C18*(1-C19) | D20: =D18*(1-D19) | E20: =E18*(1-E19) | F20: =F18*(1-F19) | G20: =G18*(1-G19) | H20: =H18*(1-H19) | I20: =I18*(1-I19) | ... K20: =K18*(1-K19)
A21: ROIC | B21: =MAX(Inputs!$B$20+$B$10,Inputs!$B$21+$B$10-(Inputs!$B$21-Inputs!$B$20)*0/9) | C21: =MAX(Inputs!$B$20+$B$10,Inputs!$B$21+$B$10-(Inputs!$B$21-Inputs!$B$20)*1/9) | D21: =MAX(Inputs!$B$20+$B$10,Inputs!$B$21+$B$10-(Inputs!$B$21-Inputs!$B$20)*2/9) | E21: =MAX(Inputs!$B$20+$B$10,Inputs!$B$21+$B$10-(Inputs!$B$21-Inputs!$B$20)*3/9) | F21: =MAX(Inputs!$B$20+$B$10,Inputs!$B$21+$B$10-(Inputs!$B$21-Inputs!$B$20)*4/9) | G21: =MAX(Inputs!$B$20+$B$10,Inputs!$B$21+$B$10-(Inputs!$B$21-Inputs!$B$20)*5/9) | H21: =MAX(Inputs!$B$20+$B$10,Inputs!$B$21+$B$10-(Inputs!$B$21-Inputs!$B$20)*6/9) | I21: =MAX(Inputs!$B$20+$B$10,Inputs!$B$21+$B$10-(Inputs!$B$21-Inputs!$B$20)*7/9) | J21: =MAX(Inputs!$B$20+$B$10,Inputs!$B$21+$B$10-(Inputs!$B$21-Inputs!$B$20)*8/9) | K21: =MAX(Inputs!$B$20+$B$10,Inputs!$B$21+$B$10-(Inputs!$B$21-Inputs!$B$20)*9/9)
A22: Reinvestment Rate | B22: =B16/B21 | C22: =C16/C21 | D22: =D16/D21 | E22: =E16/E21 | F22: =F16/F21 | G22: =G16/G21 | H22: =H16/H21 | I22: =I16/I21 | ... K22: =K16/K21
A23: Reinvestment | B23: =B20*B22 | C23: =C20*C22 | D23: =D20*D22 | E23: =E20*E22 | F23: =F20*F22 | G23: =G20*G22 | H23: =H20*H22 | I23: =I20*I22 | ... K23: =K20*K22
A24: FCFF | B24: =B20-B23 | C24: =C20-C23 | D24: =D20-D23 | E24: =E20-E23 | F24: =F20-F23 | G24: =G20-G23 | H24: =H20-H23 | I24: =I20-I23 | ... K24: =K20-K23
A25: Discount Factor | B25: =1/(1+$B$11)^1 | C25: =1/(1+$B$11)^2 | D25: =1/(1+$B$11)^3 | E25: =1/(1+$B$11)^4 | F25: =1/(1+$B$11)^5 | G25: =1/(1+$B$11)^6 | H25: =1/(1+$B$11)^7 | I25: =1/(1+$B$11)^8 | J25: =1/(1+$B$11)^9 | K25: =1/(1+$B$11)^10
A26: PV of FCFF | B26: =B24*B25 | C26: =C24*C25 | D26: =D24*D25 | E26: =E24*E25 | F26: =F24*F25 | G26: =G24*G25 | H26: =H24*H25 | I26: =I24*I25 | ... K26: =K24*K25
A29: Terminal Value & Equity Value
A30: Terminal growth | B30: =$B$12
A31: Terminal ROIC | B31: =Inputs!$B$20+$B$10
A32: Terminal reinvestment rate | B32: =B30/B31
A33: Terminal FCFF | B33: =K20*(1+B30)*(1-B32)
A34: Terminal value | B34: =B33/($B$11-B30)
A35: PV of explicit FCFF | B35: =SUM(B26:K26)
A36: PV of terminal value | B36: =B34/(1+$B$11)^10
A37: Enterprise value | B37: =B35+B36
A38: Less net debt | B38: =Inputs!$B$8
A39: Equity value | B39: =B37-B38
A40: Diluted shares | B40: =Inputs!$B$5
A41: Intrinsic value / share | B41: =B39/B40
A42: Terminal value / EV | B42: =B36/B37

Sheet Scenario Summary
A1: Probability-Weighted Scenario Valuation
A3: Scenario Valuation Table
A4: Scenario | B4: Probability | C4: Standalone Intrinsic Value/Share | D4: Probability × Value | E4: Key Case
A5: =Scenarios!A5 | B5: =Scenarios!B5 | C5: ='DCF-SevereBear'!B41 | D5: =B5*C5 | E5: =Scenarios!H5
A6: =Scenarios!A6 | B6: =Scenarios!B6 | C6: ='DCF-Bear'!B41 | D6: =B6*C6 | E6: =Scenarios!H6
A7: =Scenarios!A7 | B7: =Scenarios!B7 | C7: ='DCF-Base'!B41 | D7: =B7*C7 | E7: =Scenarios!H7
A8: =Scenarios!A8 | B8: =Scenarios!B8 | C8: ='DCF-Bull'!B41 | D8: =B8*C8 | E8: =Scenarios!H8
A9: =Scenarios!A9 | B9: =Scenarios!B9 | C9: ='DCF-ExtremeBull'!B41 | D9: =B9*C9 | E9: =Scenarios!H9
A10: Total / Expected Value | B10: =SUM(B5:B9) | C10: — | D10: =SUM(D5:D9)
A12: Outputs
A13: Probability-weighted intrinsic value / share | B13: =D10
A14: Current market price / share | B14: =Inputs!B4
A15: Expected upside / downside | B15: =B13/B14-1
A16: Investment horizon (years) | B16: 5
A17: Expected annualized return | B17: =(B13/B14)^(1/B16)-1
A19: Each scenario has its own complete 10-year FCFF DCF sheet with its own revenue growth, EBIT margin, ROIC/reinvestment, WACC and terminal assumptions. This summary only pulls the five standalone DCF results and probability-weights them — the summary never feeds back into any DCF, so there are no circular references.

Sheet Reverse DCF
A1: Reverse DCF — Market-Implied Fundamentals
A3: Market Inputs
A4: Current price | B4: =Inputs!B4
A5: Diluted shares | B5: =Inputs!B5
A6: Equity market value | B6: =B4*B5
A7: Net debt | B7: =Inputs!B8
A8: Enterprise value implied by price | B8: =B6+B7
A9: WACC | B9: =Inputs!B18
A10: Terminal growth | B10: =Inputs!B19
A13: Reverse DCF Grid — terminal revenue and margin combinations
A14: Terminal Revenue | B14: 6 | C14: 7 | D14: 8 | E14: 9 | F14: 10 | G14: 11 | H14: 12 | I14: 13 | J14: 14
A15: 0.2 | B15: =(B$14*$A15*(1-Inputs!$B$17)*(1-$B$9/Inputs!$B$20))/($B$10-$B$11) | C15: =(C$14*$A15*(1-Inputs!$B$17)*(1-$B$9/Inputs!$B$20))/($B$10-$B$11) | D15: =(D$14*$A15*(1-Inputs!$B$17)*(1-$B$9/Inputs!$B$20))/($B$10-$B$11) | E15: =(E$14*$A15*(1-Inputs!$B$17)*(1-$B$9/Inputs!$B$20))/($B$10-$B$11) | F15: =(F$14*$A15*(1-Inputs!$B$17)*(1-$B$9/Inputs!$B$20))/($B$10-$B$11) | G15: =(G$14*$A15*(1-Inputs!$B$17)*(1-$B$9/Inputs!$B$20))/($B$10-$B$11) | H15: =(H$14*$A15*(1-Inputs!$B$17)*(1-$B$9/Inputs!$B$20))/($B$10-$B$11) | I15: =(I$14*$A15*(1-Inputs!$B$17)*(1-$B$9/Inputs!$B$20))/($B$10-$B$11) | J15: =(J$14*$A15*(1-Inputs!$B$17)*(1-$B$9/Inputs!$B$20))/($B$10-$B$11)
A16: 0.25 | B16: =(B$14*$A16*(1-Inputs!$B$17)*(1-$B$9/Inputs!$B$20))/($B$10-$B$11) | C16: =(C$14*$A16*(1-Inputs!$B$17)*(1-$B$9/Inputs!$B$20))/($B$10-$B$11) | D16: =(D$14*$A16*(1-Inputs!$B$17)*(1-$B$9/Inputs!$B$20))/($B$10-$B$11) | E16: =(E$14*$A16*(1-Inputs!$B$17)*(1-$B$9/Inputs!$B$20))/($B$10-$B$11) | F16: =(F$14*$A16*(1-Inputs!$B$17)*(1-$B$9/Inputs!$B$20))/($B$10-$B$11) | G16: =(G$14*$A16*(1-Inputs!$B$17)*(1-$B$9/Inputs!$B$20))/($B$10-$B$11) | H16: =(H$14*$A16*(1-Inputs!$B$17)*(1-$B$9/Inputs!$B$20))/($B$10-$B$11) | I16: =(I$14*$A16*(1-Inputs!$B$17)*(1-$B$9/Inputs!$B$20))/($B$10-$B$11) | J16: =(J$14*$A16*(1-Inputs!$B$17)*(1-$B$9/Inputs!$B$20))/($B$10-$B$11)
A17: 0.3 | B17: =(B$14*$A17*(1-Inputs!$B$17)*(1-$B$9/Inputs!$B$20))/($B$10-$B$11) | C17: =(C$14*$A17*(1-Inputs!$B$17)*(1-$B$9/Inputs!$B$20))/($B$10-$B$11) | D17: =(D$14*$A17*(1-Inputs!$B$17)*(1-$B$9/Inputs!$B$20))/($B$10-$B$11) | E17: =(E$14*$A17*(1-Inputs!$B$17)*(1-$B$9/Inputs!$B$20))/($B$10-$B$11) | F17: =(F$14*$A17*(1-Inputs!$B$17)*(1-$B$9/Inputs!$B$20))/($B$10-$B$11) | G17: =(G$14*$A17*(1-Inputs!$B$17)*(1-$B$9/Inputs!$B$20))/($B$10-$B$11) | H17: =(H$14*$A17*(1-Inputs!$B$17)*(1-$B$9/Inputs!$B$20))/($B$10-$B$11) | I17: =(I$14*$A17*(1-Inputs!$B$17)*(1-$B$9/Inputs!$B$20))/($B$10-$B$11) | J17: =(J$14*$A17*(1-Inputs!$B$17)*(1-$B$9/Inputs!$B$20))/($B$10-$B$11)
A18: 0.35 | B18: =(B$14*$A18*(1-Inputs!$B$17)*(1-$B$9/Inputs!$B$20))/($B$10-$B$11) | C18: =(C$14*$A18*(1-Inputs!$B$17)*(1-$B$9/Inputs!$B$20))/($B$10-$B$11) | D18: =(D$14*$A18*(1-Inputs!$B$17)*(1-$B$9/Inputs!$B$20))/($B$10-$B$11) | E18: =(E$14*$A18*(1-Inputs!$B$17)*(1-$B$9/Inputs!$B$20))/($B$10-$B$11) | F18: =(F$14*$A18*(1-Inputs!$B$17)*(1-$B$9/Inputs!$B$20))/($B$10-$B$11) | G18: =(G$14*$A18*(1-Inputs!$B$17)*(1-$B$9/Inputs!$B$20))/($B$10-$B$11) | H18: =(H$14*$A18*(1-Inputs!$B$17)*(1-$B$9/Inputs!$B$20))/($B$10-$B$11) | I18: =(I$14*$A18*(1-Inputs!$B$17)*(1-$B$9/Inputs!$B$20))/($B$10-$B$11) | J18: =(J$14*$A18*(1-Inputs!$B$17)*(1-$B$9/Inputs!$B$20))/($B$10-$B$11)
A19: 0.4 | B19: =(B$14*$A19*(1-Inputs!$B$17)*(1-$B$9/Inputs!$B$20))/($B$10-$B$11) | C19: =(C$14*$A19*(1-Inputs!$B$17)*(1-$B$9/Inputs!$B$20))/($B$10-$B$11) | D19: =(D$14*$A19*(1-Inputs!$B$17)*(1-$B$9/Inputs!$B$20))/($B$10-$B$11) | E19: =(E$14*$A19*(1-Inputs!$B$17)*(1-$B$9/Inputs!$B$20))/($B$10-$B$11) | F19: =(F$14*$A19*(1-Inputs!$B$17)*(1-$B$9/Inputs!$B$20))/($B$10-$B$11) | G19: =(G$14*$A19*(1-Inputs!$B$17)*(1-$B$9/Inputs!$B$20))/($B$10-$B$11) | H19: =(H$14*$A19*(1-Inputs!$B$17)*(1-$B$9/Inputs!$B$20))/($B$10-$B$11) | I19: =(I$14*$A19*(1-Inputs!$B$17)*(1-$B$9/Inputs!$B$20))/($B$10-$B$11) | J19: =(J$14*$A19*(1-Inputs!$B$17)*(1-$B$9/Inputs!$B$20))/($B$10-$B$11)
A20: 0.45 | B20: =(B$14*$A20*(1-Inputs!$B$17)*(1-$B$9/Inputs!$B$20))/($B$10-$B$11) | C20: =(C$14*$A20*(1-Inputs!$B$17)*(1-$B$9/Inputs!$B$20))/($B$10-$B$11) | D20: =(D$14*$A20*(1-Inputs!$B$17)*(1-$B$9/Inputs!$B$20))/($B$10-$B$11) | E20: =(E$14*$A20*(1-Inputs!$B$17)*(1-$B$9/Inputs!$B$20))/($B$10-$B$11) | F20: =(F$14*$A20*(1-Inputs!$B$17)*(1-$B$9/Inputs!$B$20))/($B$10-$B$11) | G20: =(G$14*$A20*(1-Inputs!$B$17)*(1-$B$9/Inputs!$B$20))/($B$10-$B$11) | H20: =(H$14*$A20*(1-Inputs!$B$17)*(1-$B$9/Inputs!$B$20))/($B$10-$B$11) | I20: =(I$14*$A20*(1-Inputs!$B$17)*(1-$B$9/Inputs!$B$20))/($B$10-$B$11) | J20: =(J$14*$A20*(1-Inputs!$B$17)*(1-$B$9/Inputs!$B$20))/($B$10-$B$11)
A21: 0.5 | B21: =(B$14*$A21*(1-Inputs!$B$17)*(1-$B$9/Inputs!$B$20))/($B$10-$B$11) | C21: =(C$14*$A21*(1-Inputs!$B$17)*(1-$B$9/Inputs!$B$20))/($B$10-$B$11) | D21: =(D$14*$A21*(1-Inputs!$B$17)*(1-$B$9/Inputs!$B$20))/($B$10-$B$11) | E21: =(E$14*$A21*(1-Inputs!$B$17)*(1-$B$9/Inputs!$B$20))/($B$10-$B$11) | F21: =(F$14*$A21*(1-Inputs!$B$17)*(1-$B$9/Inputs!$B$20))/($B$10-$B$11) | G21: =(G$14*$A21*(1-Inputs!$B$17)*(1-$B$9/Inputs!$B$20))/($B$10-$B$11) | H21: =(H$14*$A21*(1-Inputs!$B$17)*(1-$B$9/Inputs!$B$20))/($B$10-$B$11) | I21: =(I$14*$A21*(1-Inputs!$B$17)*(1-$B$9/Inputs!$B$20))/($B$10-$B$11) | J21: =(J$14*$A21*(1-Inputs!$B$17)*(1-$B$9/Inputs!$B$20))/($B$10-$B$11)
A23: Grid cells are terminal EV in $ billions. Compare against implied EV above.
A24: This is a simplified inversion; use the full DCF sheet for detailed annual assumptions.

Sheet Sensitivity
A1: Valuation Sensitivities
A3: WACC × Terminal Growth — Approximate DCF Share Value
A4: WACC \ g | B4: 0.02 | C4: 0.025 | D4: 0.03 | E4: 0.035 | F4: 0.04
A5: 0.095 | B5: =('DCF-Base'!$B$35+('DCF-Base'!$B$33/($A5-B$4))/(1+$A5)^10-Inputs!$B$8)/Inputs!$B$5 | C5: =('DCF-Base'!$B$35+('DCF-Base'!$B$33/($A5-C$4))/(1+$A5)^10-Inputs!$B$8)/Inputs!$B$5 | D5: =('DCF-Base'!$B$35+('DCF-Base'!$B$33/($A5-D$4))/(1+$A5)^10-Inputs!$B$8)/Inputs!$B$5 | E5: =('DCF-Base'!$B$35+('DCF-Base'!$B$33/($A5-E$4))/(1+$A5)^10-Inputs!$B$8)/Inputs!$B$5 | F5: =('DCF-Base'!$B$35+('DCF-Base'!$B$33/($A5-F$4))/(1+$A5)^10-Inputs!$B$8)/Inputs!$B$5
A6: 0.105 | B6: =('DCF-Base'!$B$35+('DCF-Base'!$B$33/($A6-B$4))/(1+$A6)^10-Inputs!$B$8)/Inputs!$B$5 | C6: =('DCF-Base'!$B$35+('DCF-Base'!$B$33/($A6-C$4))/(1+$A6)^10-Inputs!$B$8)/Inputs!$B$5 | D6: =('DCF-Base'!$B$35+('DCF-Base'!$B$33/($A6-D$4))/(1+$A6)^10-Inputs!$B$8)/Inputs!$B$5 | E6: =('DCF-Base'!$B$35+('DCF-Base'!$B$33/($A6-E$4))/(1+$A6)^10-Inputs!$B$8)/Inputs!$B$5 | F6: =('DCF-Base'!$B$35+('DCF-Base'!$B$33/($A6-F$4))/(1+$A6)^10-Inputs!$B$8)/Inputs!$B$5
A7: 0.115 | B7: =('DCF-Base'!$B$35+('DCF-Base'!$B$33/($A7-B$4))/(1+$A7)^10-Inputs!$B$8)/Inputs!$B$5 | C7: =('DCF-Base'!$B$35+('DCF-Base'!$B$33/($A7-C$4))/(1+$A7)^10-Inputs!$B$8)/Inputs!$B$5 | D7: =('DCF-Base'!$B$35+('DCF-Base'!$B$33/($A7-D$4))/(1+$A7)^10-Inputs!$B$8)/Inputs!$B$5 | E7: =('DCF-Base'!$B$35+('DCF-Base'!$B$33/($A7-E$4))/(1+$A7)^10-Inputs!$B$8)/Inputs!$B$5 | F7: =('DCF-Base'!$B$35+('DCF-Base'!$B$33/($A7-F$4))/(1+$A7)^10-Inputs!$B$8)/Inputs!$B$5
A8: 0.125 | B8: =('DCF-Base'!$B$35+('DCF-Base'!$B$33/($A8-B$4))/(1+$A8)^10-Inputs!$B$8)/Inputs!$B$5 | C8: =('DCF-Base'!$B$35+('DCF-Base'!$B$33/($A8-C$4))/(1+$A8)^10-Inputs!$B$8)/Inputs!$B$5 | D8: =('DCF-Base'!$B$35+('DCF-Base'!$B$33/($A8-D$4))/(1+$A8)^10-Inputs!$B$8)/Inputs!$B$5 | E8: =('DCF-Base'!$B$35+('DCF-Base'!$B$33/($A8-E$4))/(1+$A8)^10-Inputs!$B$8)/Inputs!$B$5 | F8: =('DCF-Base'!$B$35+('DCF-Base'!$B$33/($A8-F$4))/(1+$A8)^10-Inputs!$B$8)/Inputs!$B$5
A9: 0.14 | B9: =('DCF-Base'!$B$35+('DCF-Base'!$B$33/($A9-B$4))/(1+$A9)^10-Inputs!$B$8)/Inputs!$B$5 | C9: =('DCF-Base'!$B$35+('DCF-Base'!$B$33/($A9-C$4))/(1+$A9)^10-Inputs!$B$8)/Inputs!$B$5 | D9: =('DCF-Base'!$B$35+('DCF-Base'!$B$33/($A9-D$4))/(1+$A9)^10-Inputs!$B$8)/Inputs!$B$5 | E9: =('DCF-Base'!$B$35+('DCF-Base'!$B$33/($A9-E$4))/(1+$A9)^10-Inputs!$B$8)/Inputs!$B$5 | F9: =('DCF-Base'!$B$35+('DCF-Base'!$B$33/($A9-F$4))/(1+$A9)^10-Inputs!$B$8)/Inputs!$B$5
A12: Terminal EBIT Margin × Mature Revenue
A13: Margin \ Revenue | B13: 6 | C13: 7 | D13: 8 | E13: 9 | F13: 10 | G13: 11 | H13: 12
A14: 0.2 | B14: =(B$13*$A14*(1-Inputs!$B$17)*(1-Inputs!$B$19/Inputs!$B$20))/((Inputs!$B$18)-Inputs!$B$19) | C14: =(C$13*$A14*(1-Inputs!$B$17)*(1-Inputs!$B$19/Inputs!$B$20))/((Inputs!$B$18)-Inputs!$B$19) | D14: =(D$13*$A14*(1-Inputs!$B$17)*(1-Inputs!$B$19/Inputs!$B$20))/((Inputs!$B$18)-Inputs!$B$19) | E14: =(E$13*$A14*(1-Inputs!$B$17)*(1-Inputs!$B$19/Inputs!$B$20))/((Inputs!$B$18)-Inputs!$B$19) | F14: =(F$13*$A14*(1-Inputs!$B$17)*(1-Inputs!$B$19/Inputs!$B$20))/((Inputs!$B$18)-Inputs!$B$19) | G14: =(G$13*$A14*(1-Inputs!$B$17)*(1-Inputs!$B$19/Inputs!$B$20))/((Inputs!$B$18)-Inputs!$B$19) | H14: =(H$13*$A14*(1-Inputs!$B$17)*(1-Inputs!$B$19/Inputs!$B$20))/((Inputs!$B$18)-Inputs!$B$19)
A15: 0.25 | B15: =(B$13*$A15*(1-Inputs!$B$17)*(1-Inputs!$B$19/Inputs!$B$20))/((Inputs!$B$18)-Inputs!$B$19) | C15: =(C$13*$A15*(1-Inputs!$B$17)*(1-Inputs!$B$19/Inputs!$B$20))/((Inputs!$B$18)-Inputs!$B$19) | D15: =(D$13*$A15*(1-Inputs!$B$17)*(1-Inputs!$B$19/Inputs!$B$20))/((Inputs!$B$18)-Inputs!$B$19) | E15: =(E$13*$A15*(1-Inputs!$B$17)*(1-Inputs!$B$19/Inputs!$B$20))/((Inputs!$B$18)-Inputs!$B$19) | F15: =(F$13*$A15*(1-Inputs!$B$17)*(1-Inputs!$B$19/Inputs!$B$20))/((Inputs!$B$18)-Inputs!$B$19) | G15: =(G$13*$A15*(1-Inputs!$B$17)*(1-Inputs!$B$19/Inputs!$B$20))/((Inputs!$B$18)-Inputs!$B$19) | H15: =(H$13*$A15*(1-Inputs!$B$17)*(1-Inputs!$B$19/Inputs!$B$20))/((Inputs!$B$18)-Inputs!$B$19)
A16: 0.3 | B16: =(B$13*$A16*(1-Inputs!$B$17)*(1-Inputs!$B$19/Inputs!$B$20))/((Inputs!$B$18)-Inputs!$B$19) | C16: =(C$13*$A16*(1-Inputs!$B$17)*(1-Inputs!$B$19/Inputs!$B$20))/((Inputs!$B$18)-Inputs!$B$19) | D16: =(D$13*$A16*(1-Inputs!$B$17)*(1-Inputs!$B$19/Inputs!$B$20))/((Inputs!$B$18)-Inputs!$B$19) | E16: =(E$13*$A16*(1-Inputs!$B$17)*(1-Inputs!$B$19/Inputs!$B$20))/((Inputs!$B$18)-Inputs!$B$19) | F16: =(F$13*$A16*(1-Inputs!$B$17)*(1-Inputs!$B$19/Inputs!$B$20))/((Inputs!$B$18)-Inputs!$B$19) | G16: =(G$13*$A16*(1-Inputs!$B$17)*(1-Inputs!$B$19/Inputs!$B$20))/((Inputs!$B$18)-Inputs!$B$19) | H16: =(H$13*$A16*(1-Inputs!$B$17)*(1-Inputs!$B$19/Inputs!$B$20))/((Inputs!$B$18)-Inputs!$B$19)
A17: 0.35 | B17: =(B$13*$A17*(1-Inputs!$B$17)*(1-Inputs!$B$19/Inputs!$B$20))/((Inputs!$B$18)-Inputs!$B$19) | C17: =(C$13*$A17*(1-Inputs!$B$17)*(1-Inputs!$B$19/Inputs!$B$20))/((Inputs!$B$18)-Inputs!$B$19) | D17: =(D$13*$A17*(1-Inputs!$B$17)*(1-Inputs!$B$19/Inputs!$B$20))/((Inputs!$B$18)-Inputs!$B$19) | E17: =(E$13*$A17*(1-Inputs!$B$17)*(1-Inputs!$B$19/Inputs!$B$20))/((Inputs!$B$18)-Inputs!$B$19) | F17: =(F$13*$A17*(1-Inputs!$B$17)*(1-Inputs!$B$19/Inputs!$B$20))/((Inputs!$B$18)-Inputs!$B$19) | G17: =(G$13*$A17*(1-Inputs!$B$17)*(1-Inputs!$B$19/Inputs!$B$20))/((Inputs!$B$18)-Inputs!$B$19) | H17: =(H$13*$A17*(1-Inputs!$B$17)*(1-Inputs!$B$19/Inputs!$B$20))/((Inputs!$B$18)-Inputs!$B$19)
A18: 0.4 | B18: =(B$13*$A18*(1-Inputs!$B$17)*(1-Inputs!$B$19/Inputs!$B$20))/((Inputs!$B$18)-Inputs!$B$19) | C18: =(C$13*$A18*(1-Inputs!$B$17)*(1-Inputs!$B$19/Inputs!$B$20))/((Inputs!$B$18)-Inputs!$B$19) | D18: =(D$13*$A18*(1-Inputs!$B$17)*(1-Inputs!$B$19/Inputs!$B$20))/((Inputs!$B$18)-Inputs!$B$19) | E18: =(E$13*$A18*(1-Inputs!$B$17)*(1-Inputs!$B$19/Inputs!$B$20))/((Inputs!$B$18)-Inputs!$B$19) | F18: =(F$13*$A18*(1-Inputs!$B$17)*(1-Inputs!$B$19/Inputs!$B$20))/((Inputs!$B$18)-Inputs!$B$19) | G18: =(G$13*$A18*(1-Inputs!$B$17)*(1-Inputs!$B$19/Inputs!$B$20))/((Inputs!$B$18)-Inputs!$B$19) | H18: =(H$13*$A18*(1-Inputs!$B$17)*(1-Inputs!$B$19/Inputs!$B$20))/((Inputs!$B$18)-Inputs!$B$19)
A19: 0.45 | B19: =(B$13*$A19*(1-Inputs!$B$17)*(1-Inputs!$B$19/Inputs!$B$20))/((Inputs!$B$18)-Inputs!$B$19) | C19: =(C$13*$A19*(1-Inputs!$B$17)*(1-Inputs!$B$19/Inputs!$B$20))/((Inputs!$B$18)-Inputs!$B$19) | D19: =(D$13*$A19*(1-Inputs!$B$17)*(1-Inputs!$B$19/Inputs!$B$20))/((Inputs!$B$18)-Inputs!$B$19) | E19: =(E$13*$A19*(1-Inputs!$B$17)*(1-Inputs!$B$19/Inputs!$B$20))/((Inputs!$B$18)-Inputs!$B$19) | F19: =(F$13*$A19*(1-Inputs!$B$17)*(1-Inputs!$B$19/Inputs!$B$20))/((Inputs!$B$18)-Inputs!$B$19) | G19: =(G$13*$A19*(1-Inputs!$B$17)*(1-Inputs!$B$19/Inputs!$B$20))/((Inputs!$B$18)-Inputs!$B$19) | H19: =(H$13*$A19*(1-Inputs!$B$17)*(1-Inputs!$B$19/Inputs!$B$20))/((Inputs!$B$18)-Inputs!$B$19)
A20: 0.5 | B20: =(B$13*$A20*(1-Inputs!$B$17)*(1-Inputs!$B$19/Inputs!$B$20))/((Inputs!$B$18)-Inputs!$B$19) | C20: =(C$13*$A20*(1-Inputs!$B$17)*(1-Inputs!$B$19/Inputs!$B$20))/((Inputs!$B$18)-Inputs!$B$19) | D20: =(D$13*$A20*(1-Inputs!$B$17)*(1-Inputs!$B$19/Inputs!$B$20))/((Inputs!$B$18)-Inputs!$B$19) | E20: =(E$13*$A20*(1-Inputs!$B$17)*(1-Inputs!$B$19/Inputs!$B$20))/((Inputs!$B$18)-Inputs!$B$19) | F20: =(F$13*$A20*(1-Inputs!$B$17)*(1-Inputs!$B$19/Inputs!$B$20))/((Inputs!$B$18)-Inputs!$B$19) | G20: =(G$13*$A20*(1-Inputs!$B$17)*(1-Inputs!$B$19/Inputs!$B$20))/((Inputs!$B$18)-Inputs!$B$19) | H20: =(H$13*$A20*(1-Inputs!$B$17)*(1-Inputs!$B$19/Inputs!$B$20))/((Inputs!$B$18)-Inputs!$B$19)
A23: Growth × ROIC — Reinvestment Logic
A24: Growth \ ROIC | B24: 0.1 | C24: 0.15 | D24: 0.2 | E24: 0.25 | F24: 0.3
A25: 0.05 | B25: =0.05/B$24 | C25: =0.05/C$24 | D25: =0.05/D$24 | E25: =0.05/E$24 | F25: =0.05/F$24
A26: 0.1 | B26: =0.1/B$24 | C26: =0.1/C$24 | D26: =0.1/D$24 | E26: =0.1/E$24 | F26: =0.1/F$24
A27: 0.15 | B27: =0.15/B$24 | C27: =0.15/C$24 | D27: =0.15/D$24 | E27: =0.15/E$24 | F27: =0.15/F$24
A28: 0.2 | B28: =0.2/B$24 | C28: =0.2/C$24 | D28: =0.2/D$24 | E28: =0.2/E$24 | F28: =0.2/F$24
A29: 0.25 | B29: =0.25/B$24 | C29: =0.25/C$24 | D29: =0.25/D$24 | E29: =0.25/E$24 | F29: =0.25/F$24

Sheet Checks
A1: Model Integrity Checks
A3: Workbook-wide checks
A4: Probability sum | B4: =SUM(Scenarios!B5:B9)
A5: Probability sum = 100% | B5: =ABS(B4-1)<0.0001
A7: Per-scenario checks
A8: Check | B8: Severe Bear | C8: Bear | D8: Base | E8: Bull | F8: Extreme Bull
A9: Terminal growth < WACC | B9: ='DCF-SevereBear'!B30<'DCF-SevereBear'!B11 | C9: ='DCF-Bear'!B30<'DCF-Bear'!B11 | D9: ='DCF-Base'!B30<'DCF-Base'!B11 | E9: ='DCF-Bull'!B30<'DCF-Bull'!B11 | F9: ='DCF-ExtremeBull'!B30<'DCF-ExtremeBull'!B11
A10: Terminal reinvestment < 100% | B10: ='DCF-SevereBear'!B32<1 | C10: ='DCF-Bear'!B32<1 | D10: ='DCF-Base'!B32<1 | E10: ='DCF-Bull'!B32<1 | F10: ='DCF-ExtremeBull'!B32<1
A11: Terminal FCFF > 0 | B11: ='DCF-SevereBear'!B33>0 | C11: ='DCF-Bear'!B33>0 | D11: ='DCF-Base'!B33>0 | E11: ='DCF-Bull'!B33>0 | F11: ='DCF-ExtremeBull'!B33>0
A12: Intrinsic value / share > 0 | B12: ='DCF-SevereBear'!B41>0 | C12: ='DCF-Bear'!B41>0 | D12: ='DCF-Base'!B41>0 | E12: ='DCF-Bull'!B41>0 | F12: ='DCF-ExtremeBull'!B41>0
A14: Green = pass. If a check fails, review assumptions before using the valuation.
